LICENSE
pyproject.toml
setup.py
ousint/__init__.py
ousint/module.py
ousint.egg-info/PKG-INFO
ousint.egg-info/SOURCES.txt
ousint.egg-info/dependency_links.txt
ousint.egg-info/top_level.txt