Metadata-Version: 2.1
Name: ousint
Version: 0.3
Summary: O futuro.
Author: OSkyDev
Author-email: skydagringa1@gmail.com
Classifier: Programming Language :: Python :: 3
Classifier: License :: OSI Approved :: MIT License
Classifier: Operating System :: OS Independent
Requires-Python: >=3.6
License-File: LICENSE
